Workbook

Sheet README
A1: ARMADA Marine Robotics — Forward Requirements / Scenario Model
A3: WHAT THIS IS
A4: A requirements model, not a projection. ARMADA has no publicly known revenue,
A5: so none is invented and no revenue history is shown. The model asks:
A6: 1. What commercial scale would ARMADA need for a venture-scale outcome?
A7: 2. What unit economics would make that plausible?
A9: WHAT THIS IS NOT
A10: Not a valuation. Not a forecast. Not an investment recommendation.
A11: Government SBIR/contract obligations are NOT treated as product revenue.
A13: COLOUR KEY
A14: Green = OBSERVED, traceable to a cited public source
A15: Amber = ANALYST ASSUMPTION, not sourced. Change these.
... A19: Generated 2026-08-21 from public sources accessed 2026-08-21.

Sheet Observed_Facts
A1: OBSERVED FACTS — every value traceable to a public source
A2: Fact | B2: Value | C2: Source / basis
A3: Total verified federal awards | B3: 2972287 | C3: USAspending + SBIR bulk, 6 distinct awards
A4: Navy Phase II obligated (N68335-23-C-0142) | B4: 1998926 | C4: base $999,028 + option $499,949 + CLIN0004 $499,949
A5: Most recent obligation | B5: 499949 | C5: Mod P00003, 2026-03-10, incrementally funding CLIN 0004
A6: Narrow addressable procurement observed (13 yrs) | B6: 10740202 | C6: components/spares + payload deployment
A7: Narrow addressable, annualised | B7: 826169 | C7: the same figure divided by the 13-year span
A8: Broad adjacency procurement, annualised | B8: 6272080 | C8: incl. platforms, sensor payloads, launch & recovery
A9: Publicly identified employees | B9: 3 | C9: armadamarinerobotics.com/team
A10: Known commercial revenue | B10: 0 | C10: no commercial sale evidenced in any public source

Sheet Assumptions
A1: ASSUMPTIONS — amber cells are ANALYST INPUTS, not sourced facts
A2: Driver | B2: Bear | C2: Base | D2: Bull | E2: Type | F2: Note
A3: EPADS pod ASP ($) | B3: 12000 | C3: 25000 | D3: 45000 | E3: ASSUMPTION | F3: No public price exists. Anchored on the $5kg A-size module form factor and defence subsystem norms. The single most sensitive input.
A4: EPADS pods sold per year (steady state) | B4: 150 | C4: 600 | D4: 2500 | E4: ASSUMPTION | F4: Pods are consumed per deployment if left on the seafloor with the payload. Volume is the core uncertainty.
A5: EPADS gross margin | B5: 0.35 | C5: 0.5 | D5: 0.6 | E5: ASSUMPTION | F5: Hardware consumable; margin depends on contract manufacturing.
A6: Propulsion module ASP ($) | B6: 20000 | C6: 40000 | D6: 70000 | E6: ASSUMPTION | F6: Durable subsystem, one per vehicle.
A7: Propulsion modules per year | B7: 20 | C7: 120 | D7: 500 | E7: ASSUMPTION | F7: Requires an OEM design-in. Zero such relationship is public today.
A8: Propulsion gross margin | B8: 0.4 | C8: 0.55 | D8: 0.65 | E8: ASSUMPTION | F8: Higher than pods; lower volume.
A9: Engineering / R&D contract revenue ($/yr) | B9: 1500000 | C9: 2000000 | D9: 2500000 | E9: OBSERVED-anchored | F9: Anchored on observed run-rate: $2,972,287 of federal awards over ~5 years, with $499,949 obligated in Mar 2026.
A10: Engineering gross margin | B10: 0.15 | C10: 0.25 | D10: 0.35 | E10: ASSUMPTION | F10: Cost-plus style R&D work carries thin margin.
A11: Support / service revenue ($/yr) | B11: 0 | C11: 250000 | D11: 900000 | E11: ASSUMPTION | F11: Speculative; no evidence of a service line today.
A12: Headcount at steady state | B12: 12 | C12: 25 | D12: 45 | E12: ASSUMPTION | F12: Three people are publicly identified today.
A13: Fully loaded cost per head ($) | B13: 190000 | C13: 210000 | D13: 230000 | E13: ASSUMPTION | F13: Massachusetts marine/defence engineering.
A14: Non-headcount opex ($/yr) | B14: 400000 | C14: 700000 | D14: 1200000 | E14: ASSUMPTION | F14: Facilities, test time, vessel time, certification, IP.
... A17: Exit revenue multiple (x) | B17: 3 | C17: 5 | D17: 8 | E17: ASSUMPTION | F17: Defence-adjacent hardware trades below software multiples.

Sheet Scenarios
A1: SCENARIO OUTPUTS — live formulas referencing 'Assumptions'
A2: Steady-state revenue build | B2: Bear | C2: Base | D2: Bull
A3: EPADS revenue | B3: =Assumptions!B3*Assumptions!B4 | C3: =Assumptions!C3*Assumptions!C4 | D3: =Assumptions!D3*Assumptions!D4
A4: Propulsion revenue | B4: =Assumptions!B6*Assumptions!B7 | C4: =Assumptions!C6*Assumptions!C7 | D4: =Assumptions!D6*Assumptions!D7
A5: Engineering revenue | B5: =Assumptions!B9 | C5: =Assumptions!C9 | D5: =Assumptions!D9
A6: Support revenue | B6: =Assumptions!B11 | C6: =Assumptions!C11 | D6: =Assumptions!D11
A7: Total revenue | B7: =SUM(B3:B6) | C7: =SUM(C3:C6) | D7: =SUM(D3:D6)
A9: Gross profit | B9: =B3*Assumptions!B5+B4*Assumptions!B8+B5*Assumptions!B10 | C9: =C3*Assumptions!C5+C4*Assumptions!C8+C5*Assumptions!C10 | D9: =D3*Assumptions!D5+D4*Assumptions!D8+D5*Assumptions!D10
A10: Operating cost | B10: =Assumptions!B12*Assumptions!B13+Assumptions!B14 | C10: =Assumptions!C12*Assumptions!C13+Assumptions!C14 | D10: =Assumptions!D12*Assumptions!D13+Assumptions!D14
A11: Operating profit | B11: =B9-B10 | C11: =C9-C10 | D11: =D9-D10
A13: Venture-scale gap | B13: =Assumptions!B16-B7 | C13: =Assumptions!C16-C7 | D13: =Assumptions!D16-D7
A14: Reaches venture scale? | B14: =IF(B13<=0,"YES","NO") | C14: =IF(C13<=0,"YES","NO") | D14: =IF(D13<=0,"YES","NO")
A15: EPADS pods/yr required to close gap alone | B15: =IF(B13<=0,0,B13/Assumptions!B3) | C15: =IF(C13<=0,0,C13/Assumptions!C3) | D15: =IF(D13<=0,0,D13/Assumptions!D3)
A16: Implied exit value at revenue multiple | B16: =B7*Assumptions!B17 | C16: =C7*Assumptions!C17 | D16: =D7*Assumptions!D17

Sheet What_Must_Be_True
A1: WHAT MUST BE TRUE FOR A VENTURE-SCALE OUTCOME
A3: Revenue threshold used | B3: =Assumptions!C16
A4: Pods/yr at Base ASP to hit threshold on EPADS alone | B4: =Assumptions!C16/Assumptions!C3
A5: Propulsion modules/yr at Base ASP to hit threshold alone | B5: =Assumptions!C16/Assumptions!C6
A6: Observed narrow addressable procurement (annualised) | B6: =Observed_Facts!B7
A7: Threshold as a multiple of observed narrow addressable | B7: =Assumptions!C16/Observed_Facts!B7
A8: Observed broad adjacency (annualised) | B8: =Observed_Facts!B8
A9: Threshold as a multiple of observed broad adjacency | B9: =Assumptions!C16/Observed_Facts!B8
A12: READ THIS: if the threshold is a large multiple of observed addressable procurement, the venture case CANNOT rest on the federal market visible in our sample. It requires OEM channel, commercial/offshore buyers, allied export, or procurement not captured by our keywords.
